plover_stitching/__init__.py
plover_stitching/commands.py
plover_stitching/stitching.py
plover_stitching-0.1.0.dist-info/DESCRIPTION.rst
plover_stitching-0.1.0.dist-info/METADATA
plover_stitching-0.1.0.dist-info/RECORD
plover_stitching-0.1.0.dist-info/WHEEL
plover_stitching-0.1.0.dist-info/entry_points.txt
plover_stitching-0.1.0.dist-info/metadata.json
plover_stitching-0.1.0.dist-info/top_level.txt
plover_stitching-0.1.0.dist-info/zip-safe
