Metadata-Version: 1.1
Name: plover_stitching
Version: 0.1.0
Summary: Stitch words like T-H-I-S using Plover strokes
Home-page: https://github.com/morinted/plover_stitching
Author: Ted Morin
Author-email: morinted@gmail.com
License: GNU General Public License v3 or later (GPLv3+)
Keywords: plover plover_plugin
Platform: UNKNOWN
Classifier: Development Status :: 4 - Beta
Classifier: Environment :: Plugins
Classifier: Intended Audience :: End Users/Desktop
Classifier: License :: OSI Approved :: GNU General Public License v3 or later (GPLv3+)
Classifier: Operating System :: OS Independent
Classifier: Programming Language :: Python :: 3
Classifier: Programming Language :: Python :: 3.6
